doc_reader/__init__.py
doc_reader/server.py
url_extractor/__init__.py
url_extractor/server.py
hwmcp-0.1.3.dist-info/METADATA
hwmcp-0.1.3.dist-info/WHEEL
hwmcp-0.1.3.dist-info/entry_points.txt
hwmcp-0.1.3.dist-info/top_level.txt
hwmcp-0.1.3.dist-info/RECORD
